{"0":{"Pron\u00fancia:":"[Na '\u03b2osa '\u03b2aka '\u03b2iti]","Falado(a)\u00a0em:":"Fiji","Regi\u00e3o:":"Melan\u00e9sia","Total de\u00a0falantes:":"339.210, segundo censo de 1996[1]","Fam\u00edlia:":"Austron\u00e9sia\u00a0Malaio-polin\u00e9sia\u00a0\u00a0Oce\u00e2nica\u00a0\u00a0\u00a0Oce\u00e2nica centro-oriental\u00a0\u00a0\u00a0\u00a0Pac\u00edfico central\u00a0\u00a0\u00a0\u00a0\u00a0Fijiano Oriental\u00a0\u00a0\u00a0\u00a0\u00a0\u00a0Fijiano","Escrita:":"Alfabeto latino","L\u00edngua oficial de:":"Fiji","ISO 639-1:":"fj","ISO 639-2:":"fij","ISO 639-3:":"fij","T\u00edtulo":"FijianoNa vosa vaka-Viti"}}