{"0":{"":"v","Nome completo":"P","Tamb\u00e9m conhecido(a) como":"L","Nascimento":"2","G\u00eanero(s)":"S","Ocupa\u00e7\u00e3o":"c","Instrumento(s)":"V","Per\u00edodo em atividade":"1","Afilia\u00e7\u00e3o(\u00f5es)":"A","P\u00e1gina oficial":"[","Crime(s)":"e","Pena":"9","Situa\u00e7\u00e3o":"r","T\u00edtulo":"L"},"1":{"":"d","Nome completo":"a","Tamb\u00e9m conhecido(a) como":"e","Nascimento":"5","G\u00eanero(s)":"a","Ocupa\u00e7\u00e3o":"a","Instrumento(s)":"o","Per\u00edodo em atividade":"9","Afilia\u00e7\u00e3o(\u00f5es)":"r","P\u00e1gina oficial":"1","Crime(s)":"s","Pena":" ","Situa\u00e7\u00e3o":"e","T\u00edtulo":"e"},"2":{"":"e","Nome completo":"u","Tamb\u00e9m conhecido(a) como":"a","Nascimento":" ","G\u00eanero(s)":"m","Ocupa\u00e7\u00e3o":"n","Instrumento(s)":"c","Per\u00edodo em atividade":"9","Afilia\u00e7\u00e3o(\u00f5es)":"t","P\u00e1gina oficial":"]","Crime(s)":"t","Pena":"a","Situa\u00e7\u00e3o":"c","T\u00edtulo":"a"},"3":{"":null,"Nome completo":"l","Tamb\u00e9m conhecido(a) como":"n","Nascimento":"d","G\u00eanero(s)":"b","Ocupa\u00e7\u00e3o":"t","Instrumento(s)":"a","Per\u00edodo em atividade":"0","Afilia\u00e7\u00e3o(\u00f5es)":" ","P\u00e1gina oficial":null,"Crime(s)":"u","Pena":"n","Situa\u00e7\u00e3o":"o","T\u00edtulo":"n"},"4":{"":null,"Nome completo":"o","Tamb\u00e9m conhecido(a) como":"d","Nascimento":"e","G\u00eanero(s)":"a","Ocupa\u00e7\u00e3o":"o","Instrumento(s)":"l","Per\u00edodo em atividade":" ","Afilia\u00e7\u00e3o(\u00f5es)":"P","P\u00e1gina oficial":null,"Crime(s)":"p","Pena":"o","Situa\u00e7\u00e3o":"r","T\u00edtulo":"d"},"5":{"":null,"Nome completo":" ","Tamb\u00e9m conhecido(a) como":"r","Nascimento":" ","G\u00eanero(s)":",","Ocupa\u00e7\u00e3o":"r","Instrumento(s)":",","Per\u00edodo em atividade":"-","Afilia\u00e7\u00e3o(\u00f5es)":"o","P\u00e1gina oficial":null,"Crime(s)":"r","Pena":"s","Situa\u00e7\u00e3o":"r","T\u00edtulo":"r"},"6":{"":null,"Nome completo":"L","Tamb\u00e9m conhecido(a) como":"o","Nascimento":"j","G\u00eanero(s)":" ","Ocupa\u00e7\u00e3o":",","Instrumento(s)":" ","Per\u00edodo em atividade":" ","Afilia\u00e7\u00e3o(\u00f5es)":"p","P\u00e1gina oficial":null,"Crime(s)":"o","Pena":",","Situa\u00e7\u00e3o":"e","T\u00edtulo":"o"},"7":{"":null,"Nome completo":"e","Tamb\u00e9m conhecido(a) como":" ","Nascimento":"a","G\u00eanero(s)":"p","Ocupa\u00e7\u00e3o":" ","Instrumento(s)":"C","Per\u00edodo em atividade":"p","Afilia\u00e7\u00e3o(\u00f5es)":"u","P\u00e1gina oficial":null,"Crime(s)":" ","Pena":" ","Situa\u00e7\u00e3o":"n","T\u00edtulo":" "},"8":{"":null,"Nome completo":"a","Tamb\u00e9m conhecido(a) como":"L","Nascimento":"n","G\u00eanero(s)":"a","Ocupa\u00e7\u00e3o":"c","Instrumento(s)":"a","Per\u00edodo em atividade":"r","Afilia\u00e7\u00e3o(\u00f5es)":"l","P\u00e1gina oficial":null,"Crime(s)":"e","Pena":"7","Situa\u00e7\u00e3o":"d","T\u00edtulo":"L"},"9":{"":null,"Nome completo":"n","Tamb\u00e9m conhecido(a) como":"e","Nascimento":"e","G\u00eanero(s)":"g","Ocupa\u00e7\u00e3o":"o","Instrumento(s)":"v","Per\u00edodo em atividade":"e","Afilia\u00e7\u00e3o(\u00f5es)":"a","P\u00e1gina oficial":null,"Crime(s)":" ","Pena":" ","Situa\u00e7\u00e3o":"o","T\u00edtulo":"e"},"10":{"":null,"Nome completo":"d","Tamb\u00e9m conhecido(a) como":"h","Nascimento":"i","G\u00eanero(s)":"o","Ocupa\u00e7\u00e3o":"m","Instrumento(s)":"a","Per\u00edodo em atividade":"s","Afilia\u00e7\u00e3o(\u00f5es)":"r","P\u00e1gina oficial":null,"Crime(s)":"c","Pena":"m","Situa\u00e7\u00e3o":" ","T\u00edtulo":"h"},"11":{"":null,"Nome completo":"r","Tamb\u00e9m conhecido(a) como":"a","Nascimento":"r","G\u00eanero(s)":"d","Ocupa\u00e7\u00e3o":"p","Instrumento(s)":"q","Per\u00edodo em atividade":"e","Afilia\u00e7\u00e3o(\u00f5es)":null,"P\u00e1gina oficial":null,"Crime(s)":"\u00e1","Pena":"e","Situa\u00e7\u00e3o":"e","T\u00edtulo":"a"},"12":{"":null,"Nome completo":"o","Tamb\u00e9m conhecido(a) como":"r","Nascimento":"o","G\u00eanero(s)":"e","Ocupa\u00e7\u00e3o":"o","Instrumento(s)":"u","Per\u00edodo em atividade":"n","Afilia\u00e7\u00e3o(\u00f5es)":null,"P\u00e1gina oficial":null,"Crime(s)":"r","Pena":"s","Situa\u00e7\u00e3o":"m","T\u00edtulo":"r"},"13":{"":null,"Nome completo":" ","Tamb\u00e9m conhecido(a) como":"t","Nascimento":" ","G\u00eanero(s)":",","Ocupa\u00e7\u00e3o":"s","Instrumento(s)":"i","Per\u00edodo em atividade":"t","Afilia\u00e7\u00e3o(\u00f5es)":null,"P\u00e1gina oficial":null,"Crime(s)":"c","Pena":"e","Situa\u00e7\u00e3o":" ","T\u00edtulo":"t"},"14":{"":null,"Nome completo":"F","Tamb\u00e9m conhecido(a) como":null,"Nascimento":"d","G\u00eanero(s)":" ","Ocupa\u00e7\u00e3o":"i","Instrumento(s)":"n","Per\u00edodo em atividade":"e","Afilia\u00e7\u00e3o(\u00f5es)":null,"P\u00e1gina oficial":null,"Crime(s)":"e","Pena":"s","Situa\u00e7\u00e3o":"l","T\u00edtulo":null},"15":{"":null,"Nome completo":"e","Tamb\u00e9m conhecido(a) como":null,"Nascimento":"e","G\u00eanero(s)":"p","Ocupa\u00e7\u00e3o":"t","Instrumento(s)":"h","Per\u00edodo em atividade":null,"Afilia\u00e7\u00e3o(\u00f5es)":null,"P\u00e1gina oficial":null,"Crime(s)":"r","Pena":" ","Situa\u00e7\u00e3o":"i","T\u00edtulo":null},"16":{"":null,"Nome completo":"r","Tamb\u00e9m conhecido(a) como":null,"Nascimento":" ","G\u00eanero(s)":"a","Ocupa\u00e7\u00e3o":"o","Instrumento(s)":"o","Per\u00edodo em atividade":null,"Afilia\u00e7\u00e3o(\u00f5es)":null,"P\u00e1gina oficial":null,"Crime(s)":"e","Pena":"e","Situa\u00e7\u00e3o":"b","T\u00edtulo":null},"17":{"":null,"Nome completo":"n","Tamb\u00e9m conhecido(a) como":null,"Nascimento":"1","G\u00eanero(s)":"g","Ocupa\u00e7\u00e3o":"r","Instrumento(s)":",","Per\u00edodo em atividade":null,"Afilia\u00e7\u00e3o(\u00f5es)":null,"P\u00e1gina oficial":null,"Crime(s)":" ","Pena":" ","Situa\u00e7\u00e3o":"e","T\u00edtulo":null},"18":{"":null,"Nome completo":"a","Tamb\u00e9m conhecido(a) como":null,"Nascimento":"9","G\u00eanero(s)":"o","Ocupa\u00e7\u00e3o":",","Instrumento(s)":" ","Per\u00edodo em atividade":null,"Afilia\u00e7\u00e3o(\u00f5es)":null,"P\u00e1gina oficial":null,"Crime(s)":"p","Pena":"6","Situa\u00e7\u00e3o":"r","T\u00edtulo":null},"19":{"":null,"Nome completo":"n","Tamb\u00e9m conhecido(a) como":null,"Nascimento":"7","G\u00eanero(s)":"d","Ocupa\u00e7\u00e3o":" ","Instrumento(s)":"B","Per\u00edodo em atividade":null,"Afilia\u00e7\u00e3o(\u00f5es)":null,"P\u00e1gina oficial":null,"Crime(s)":"r","Pena":" ","Situa\u00e7\u00e3o":"d","T\u00edtulo":null},"20":{"":null,"Nome completo":"d","Tamb\u00e9m conhecido(a) como":null,"Nascimento":"2","G\u00eanero(s)":"e","Ocupa\u00e7\u00e3o":"a","Instrumento(s)":"a","Per\u00edodo em atividade":null,"Afilia\u00e7\u00e3o(\u00f5es)":null,"P\u00e1gina oficial":null,"Crime(s)":"i","Pena":"d","Situa\u00e7\u00e3o":"a","T\u00edtulo":null},"21":{"":null,"Nome completo":"e","Tamb\u00e9m conhecido(a) como":null,"Nascimento":"\u00a0","G\u00eanero(s)":" ","Ocupa\u00e7\u00e3o":"t","Instrumento(s)":"n","Per\u00edodo em atividade":null,"Afilia\u00e7\u00e3o(\u00f5es)":null,"P\u00e1gina oficial":null,"Crime(s)":"v","Pena":"i","Situa\u00e7\u00e3o":"d","T\u00edtulo":null},"22":{"":null,"Nome completo":"s","Tamb\u00e9m conhecido(a) como":null,"Nascimento":"(","G\u00eanero(s)":"r","Ocupa\u00e7\u00e3o":"i","Instrumento(s)":"j","Per\u00edodo em atividade":null,"Afilia\u00e7\u00e3o(\u00f5es)":null,"P\u00e1gina oficial":null,"Crime(s)":"a","Pena":"a","Situa\u00e7\u00e3o":"e","T\u00edtulo":null},"23":{"":null,"Nome completo":" ","Tamb\u00e9m conhecido(a) como":null,"Nascimento":"5","G\u00eanero(s)":"o","Ocupa\u00e7\u00e3o":"v","Instrumento(s)":"o","Per\u00edodo em atividade":null,"Afilia\u00e7\u00e3o(\u00f5es)":null,"P\u00e1gina oficial":null,"Crime(s)":"d","Pena":"s","Situa\u00e7\u00e3o":null,"T\u00edtulo":null},"24":{"":null,"Nome completo":"S","Tamb\u00e9m conhecido(a) como":null,"Nascimento":"3","G\u00eanero(s)":"m","Ocupa\u00e7\u00e3o":"i","Instrumento(s)":",","Per\u00edodo em atividade":null,"Afilia\u00e7\u00e3o(\u00f5es)":null,"P\u00e1gina oficial":null,"Crime(s)":"o","Pena":" ","Situa\u00e7\u00e3o":null,"T\u00edtulo":null},"25":{"":null,"Nome completo":"o","Tamb\u00e9m conhecido(a) como":null,"Nascimento":"\u00a0","G\u00eanero(s)":"\u00e2","Ocupa\u00e7\u00e3o":"s","Instrumento(s)":" ","Per\u00edodo em atividade":null,"Afilia\u00e7\u00e3o(\u00f5es)":null,"P\u00e1gina oficial":null,"Crime(s)":null,"Pena":"d","Situa\u00e7\u00e3o":null,"T\u00edtulo":null},"26":{"":null,"Nome completo":"a","Tamb\u00e9m conhecido(a) como":null,"Nascimento":"a","G\u00eanero(s)":"n","Ocupa\u00e7\u00e3o":"t","Instrumento(s)":"P","Per\u00edodo em atividade":null,"Afilia\u00e7\u00e3o(\u00f5es)":null,"P\u00e1gina oficial":null,"Crime(s)":null,"Pena":"e","Situa\u00e7\u00e3o":null,"T\u00edtulo":null},"27":{"":null,"Nome completo":"r","Tamb\u00e9m conhecido(a) como":null,"Nascimento":"n","G\u00eanero(s)":"t","Ocupa\u00e7\u00e3o":"a","Instrumento(s)":"i","Per\u00edodo em atividade":null,"Afilia\u00e7\u00e3o(\u00f5es)":null,"P\u00e1gina oficial":null,"Crime(s)":null,"Pena":" ","Situa\u00e7\u00e3o":null,"T\u00edtulo":null},"28":{"":null,"Nome completo":"e","Tamb\u00e9m conhecido(a) como":null,"Nascimento":"o","G\u00eanero(s)":"i","Ocupa\u00e7\u00e3o":" ","Instrumento(s)":"a","Per\u00edodo em atividade":null,"Afilia\u00e7\u00e3o(\u00f5es)":null,"P\u00e1gina oficial":null,"Crime(s)":null,"Pena":"r","Situa\u00e7\u00e3o":null,"T\u00edtulo":null},"29":{"":null,"Nome completo":"s","Tamb\u00e9m conhecido(a) como":null,"Nascimento":"s","G\u00eanero(s)":"c","Ocupa\u00e7\u00e3o":"s","Instrumento(s)":"n","Per\u00edodo em atividade":null,"Afilia\u00e7\u00e3o(\u00f5es)":null,"P\u00e1gina oficial":null,"Crime(s)":null,"Pena":"e","Situa\u00e7\u00e3o":null,"T\u00edtulo":null},"30":{"":null,"Nome completo":null,"Tamb\u00e9m conhecido(a) como":null,"Nascimento":")","G\u00eanero(s)":"o","Ocupa\u00e7\u00e3o":"o","Instrumento(s)":"o","Per\u00edodo em atividade":null,"Afilia\u00e7\u00e3o(\u00f5es)":null,"P\u00e1gina oficial":null,"Crime(s)":null,"Pena":"c","Situa\u00e7\u00e3o":null,"T\u00edtulo":null},"31":{"":null,"Nome completo":null,"Tamb\u00e9m conhecido(a) como":null,"Nascimento":"S","G\u00eanero(s)":",","Ocupa\u00e7\u00e3o":"c","Instrumento(s)":",","Per\u00edodo em atividade":null,"Afilia\u00e7\u00e3o(\u00f5es)":null,"P\u00e1gina oficial":null,"Crime(s)":null,"Pena":"l","Situa\u00e7\u00e3o":null,"T\u00edtulo":null},"32":{"":null,"Nome completo":null,"Tamb\u00e9m conhecido(a) como":null,"Nascimento":"\u00e3","G\u00eanero(s)":" ","Ocupa\u00e7\u00e3o":"i","Instrumento(s)":" ","Per\u00edodo em atividade":null,"Afilia\u00e7\u00e3o(\u00f5es)":null,"P\u00e1gina oficial":null,"Crime(s)":null,"Pena":"u","Situa\u00e7\u00e3o":null,"T\u00edtulo":null},"33":{"":null,"Nome completo":null,"Tamb\u00e9m conhecido(a) como":null,"Nascimento":"o","G\u00eanero(s)":"s","Ocupa\u00e7\u00e3o":"a","Instrumento(s)":"V","Per\u00edodo em atividade":null,"Afilia\u00e7\u00e3o(\u00f5es)":null,"P\u00e1gina oficial":null,"Crime(s)":null,"Pena":"s","Situa\u00e7\u00e3o":null,"T\u00edtulo":null},"34":{"":null,"Nome completo":null,"Tamb\u00e9m conhecido(a) como":null,"Nascimento":" ","G\u00eanero(s)":"a","Ocupa\u00e7\u00e3o":"l","Instrumento(s)":"i","Per\u00edodo em atividade":null,"Afilia\u00e7\u00e3o(\u00f5es)":null,"P\u00e1gina oficial":null,"Crime(s)":null,"Pena":"\u00e3","Situa\u00e7\u00e3o":null,"T\u00edtulo":null},"35":{"":null,"Nome completo":null,"Tamb\u00e9m conhecido(a) como":null,"Nascimento":"P","G\u00eanero(s)":"m","Ocupa\u00e7\u00e3o":",","Instrumento(s)":"o","Per\u00edodo em atividade":null,"Afilia\u00e7\u00e3o(\u00f5es)":null,"P\u00e1gina oficial":null,"Crime(s)":null,"Pena":"o","Situa\u00e7\u00e3o":null,"T\u00edtulo":null},"36":{"":null,"Nome completo":null,"Tamb\u00e9m conhecido(a) como":null,"Nascimento":"a","G\u00eanero(s)":"b","Ocupa\u00e7\u00e3o":" ","Instrumento(s)":"l","Per\u00edodo em atividade":null,"Afilia\u00e7\u00e3o(\u00f5es)":null,"P\u00e1gina oficial":null,"Crime(s)":null,"Pena":" ","Situa\u00e7\u00e3o":null,"T\u00edtulo":null},"37":{"":null,"Nome completo":null,"Tamb\u00e9m conhecido(a) como":null,"Nascimento":"u","G\u00eanero(s)":"a","Ocupa\u00e7\u00e3o":"e","Instrumento(s)":"\u00e3","Per\u00edodo em atividade":null,"Afilia\u00e7\u00e3o(\u00f5es)":null,"P\u00e1gina oficial":null,"Crime(s)":null,"Pena":"e","Situa\u00e7\u00e3o":null,"T\u00edtulo":null},"38":{"":null,"Nome completo":null,"Tamb\u00e9m conhecido(a) como":null,"Nascimento":"l","G\u00eanero(s)":"-","Ocupa\u00e7\u00e3o":"s","Instrumento(s)":"o","Per\u00edodo em atividade":null,"Afilia\u00e7\u00e3o(\u00f5es)":null,"P\u00e1gina oficial":null,"Crime(s)":null,"Pena":" ","Situa\u00e7\u00e3o":null,"T\u00edtulo":null},"39":{"":null,"Nome completo":null,"Tamb\u00e9m conhecido(a) como":null,"Nascimento":"o","G\u00eanero(s)":"r","Ocupa\u00e7\u00e3o":"c","Instrumento(s)":",","Per\u00edodo em atividade":null,"Afilia\u00e7\u00e3o(\u00f5es)":null,"P\u00e1gina oficial":null,"Crime(s)":null,"Pena":"2","Situa\u00e7\u00e3o":null,"T\u00edtulo":null},"40":{"":null,"Nome completo":null,"Tamb\u00e9m conhecido(a) como":null,"Nascimento":",","G\u00eanero(s)":"o","Ocupa\u00e7\u00e3o":"r","Instrumento(s)":" ","Per\u00edodo em atividade":null,"Afilia\u00e7\u00e3o(\u00f5es)":null,"P\u00e1gina oficial":null,"Crime(s)":null,"Pena":"4","Situa\u00e7\u00e3o":null,"T\u00edtulo":null},"41":{"":null,"Nome completo":null,"Tamb\u00e9m conhecido(a) como":null,"Nascimento":" ","G\u00eanero(s)":"c","Ocupa\u00e7\u00e3o":"i","Instrumento(s)":"G","Per\u00edodo em atividade":null,"Afilia\u00e7\u00e3o(\u00f5es)":null,"P\u00e1gina oficial":null,"Crime(s)":null,"Pena":" ","Situa\u00e7\u00e3o":null,"T\u00edtulo":null},"42":{"":null,"Nome completo":null,"Tamb\u00e9m conhecido(a) como":null,"Nascimento":"S","G\u00eanero(s)":"k","Ocupa\u00e7\u00e3o":"t","Instrumento(s)":"u","Per\u00edodo em atividade":null,"Afilia\u00e7\u00e3o(\u00f5es)":null,"P\u00e1gina oficial":null,"Crime(s)":null,"Pena":"d","Situa\u00e7\u00e3o":null,"T\u00edtulo":null},"43":{"":null,"Nome completo":null,"Tamb\u00e9m conhecido(a) como":null,"Nascimento":"\u00e3","G\u00eanero(s)":",","Ocupa\u00e7\u00e3o":"o","Instrumento(s)":"i","Per\u00edodo em atividade":null,"Afilia\u00e7\u00e3o(\u00f5es)":null,"P\u00e1gina oficial":null,"Crime(s)":null,"Pena":"i","Situa\u00e7\u00e3o":null,"T\u00edtulo":null},"44":{"":null,"Nome completo":null,"Tamb\u00e9m conhecido(a) como":null,"Nascimento":"o","G\u00eanero(s)":" ","Ocupa\u00e7\u00e3o":"r","Instrumento(s)":"t","Per\u00edodo em atividade":null,"Afilia\u00e7\u00e3o(\u00f5es)":null,"P\u00e1gina oficial":null,"Crime(s)":null,"Pena":"a","Situa\u00e7\u00e3o":null,"T\u00edtulo":null},"45":{"":null,"Nome completo":null,"Tamb\u00e9m conhecido(a) como":null,"Nascimento":" ","G\u00eanero(s)":"s","Ocupa\u00e7\u00e3o":null,"Instrumento(s)":"a","Per\u00edodo em atividade":null,"Afilia\u00e7\u00e3o(\u00f5es)":null,"P\u00e1gina oficial":null,"Crime(s)":null,"Pena":"s","Situa\u00e7\u00e3o":null,"T\u00edtulo":null},"46":{"":null,"Nome completo":null,"Tamb\u00e9m conhecido(a) como":null,"Nascimento":"P","G\u00eanero(s)":"o","Ocupa\u00e7\u00e3o":null,"Instrumento(s)":"r","Per\u00edodo em atividade":null,"Afilia\u00e7\u00e3o(\u00f5es)":null,"P\u00e1gina oficial":null,"Crime(s)":null,"Pena":"-","Situa\u00e7\u00e3o":null,"T\u00edtulo":null},"47":{"":null,"Nome completo":null,"Tamb\u00e9m conhecido(a) como":null,"Nascimento":"a","G\u00eanero(s)":"u","Ocupa\u00e7\u00e3o":null,"Instrumento(s)":"r","Per\u00edodo em atividade":null,"Afilia\u00e7\u00e3o(\u00f5es)":null,"P\u00e1gina oficial":null,"Crime(s)":null,"Pena":"m","Situa\u00e7\u00e3o":null,"T\u00edtulo":null},"48":{"":null,"Nome completo":null,"Tamb\u00e9m conhecido(a) como":null,"Nascimento":"u","G\u00eanero(s)":"l","Ocupa\u00e7\u00e3o":null,"Instrumento(s)":"a","Per\u00edodo em atividade":null,"Afilia\u00e7\u00e3o(\u00f5es)":null,"P\u00e1gina oficial":null,"Crime(s)":null,"Pena":"u","Situa\u00e7\u00e3o":null,"T\u00edtulo":null},"49":{"":null,"Nome completo":null,"Tamb\u00e9m conhecido(a) como":null,"Nascimento":"l","G\u00eanero(s)":",","Ocupa\u00e7\u00e3o":null,"Instrumento(s)":",","Per\u00edodo em atividade":null,"Afilia\u00e7\u00e3o(\u00f5es)":null,"P\u00e1gina oficial":null,"Crime(s)":null,"Pena":"l","Situa\u00e7\u00e3o":null,"T\u00edtulo":null},"50":{"":null,"Nome completo":null,"Tamb\u00e9m conhecido(a) como":null,"Nascimento":"o","G\u00eanero(s)":"[","Ocupa\u00e7\u00e3o":null,"Instrumento(s)":" ","Per\u00edodo em atividade":null,"Afilia\u00e7\u00e3o(\u00f5es)":null,"P\u00e1gina oficial":null,"Crime(s)":null,"Pena":"t","Situa\u00e7\u00e3o":null,"T\u00edtulo":null},"51":{"":null,"Nome completo":null,"Tamb\u00e9m conhecido(a) como":null,"Nascimento":",","G\u00eanero(s)":"1","Ocupa\u00e7\u00e3o":null,"Instrumento(s)":"P","Per\u00edodo em atividade":null,"Afilia\u00e7\u00e3o(\u00f5es)":null,"P\u00e1gina oficial":null,"Crime(s)":null,"Pena":"a","Situa\u00e7\u00e3o":null,"T\u00edtulo":null},"52":{"":null,"Nome completo":null,"Tamb\u00e9m conhecido(a) como":null,"Nascimento":" ","G\u00eanero(s)":"]","Ocupa\u00e7\u00e3o":null,"Instrumento(s)":"e","Per\u00edodo em atividade":null,"Afilia\u00e7\u00e3o(\u00f5es)":null,"P\u00e1gina oficial":null,"Crime(s)":null,"Pena":null,"Situa\u00e7\u00e3o":null,"T\u00edtulo":null},"53":{"":null,"Nome completo":null,"Tamb\u00e9m conhecido(a) como":null,"Nascimento":"B","G\u00eanero(s)":" ","Ocupa\u00e7\u00e3o":null,"Instrumento(s)":"r","Per\u00edodo em atividade":null,"Afilia\u00e7\u00e3o(\u00f5es)":null,"P\u00e1gina oficial":null,"Crime(s)":null,"Pena":null,"Situa\u00e7\u00e3o":null,"T\u00edtulo":null},"54":{"":null,"Nome completo":null,"Tamb\u00e9m conhecido(a) como":null,"Nascimento":"r","G\u00eanero(s)":"f","Ocupa\u00e7\u00e3o":null,"Instrumento(s)":"c","Per\u00edodo em atividade":null,"Afilia\u00e7\u00e3o(\u00f5es)":null,"P\u00e1gina oficial":null,"Crime(s)":null,"Pena":null,"Situa\u00e7\u00e3o":null,"T\u00edtulo":null},"55":{"":null,"Nome completo":null,"Tamb\u00e9m conhecido(a) como":null,"Nascimento":"a","G\u00eanero(s)":"u","Ocupa\u00e7\u00e3o":null,"Instrumento(s)":"u","Per\u00edodo em atividade":null,"Afilia\u00e7\u00e3o(\u00f5es)":null,"P\u00e1gina oficial":null,"Crime(s)":null,"Pena":null,"Situa\u00e7\u00e3o":null,"T\u00edtulo":null},"56":{"":null,"Nome completo":null,"Tamb\u00e9m conhecido(a) como":null,"Nascimento":"s","G\u00eanero(s)":"n","Ocupa\u00e7\u00e3o":null,"Instrumento(s)":"s","Per\u00edodo em atividade":null,"Afilia\u00e7\u00e3o(\u00f5es)":null,"P\u00e1gina oficial":null,"Crime(s)":null,"Pena":null,"Situa\u00e7\u00e3o":null,"T\u00edtulo":null},"57":{"":null,"Nome completo":null,"Tamb\u00e9m conhecido(a) como":null,"Nascimento":"i","G\u00eanero(s)":"k","Ocupa\u00e7\u00e3o":null,"Instrumento(s)":"s","Per\u00edodo em atividade":null,"Afilia\u00e7\u00e3o(\u00f5es)":null,"P\u00e1gina oficial":null,"Crime(s)":null,"Pena":null,"Situa\u00e7\u00e3o":null,"T\u00edtulo":null},"58":{"":null,"Nome completo":null,"Tamb\u00e9m conhecido(a) como":null,"Nascimento":"l","G\u00eanero(s)":",","Ocupa\u00e7\u00e3o":null,"Instrumento(s)":"\u00e3","Per\u00edodo em atividade":null,"Afilia\u00e7\u00e3o(\u00f5es)":null,"P\u00e1gina oficial":null,"Crime(s)":null,"Pena":null,"Situa\u00e7\u00e3o":null,"T\u00edtulo":null},"59":{"":null,"Nome completo":null,"Tamb\u00e9m conhecido(a) como":null,"Nascimento":null,"G\u00eanero(s)":" ","Ocupa\u00e7\u00e3o":null,"Instrumento(s)":"o","Per\u00edodo em atividade":null,"Afilia\u00e7\u00e3o(\u00f5es)":null,"P\u00e1gina oficial":null,"Crime(s)":null,"Pena":null,"Situa\u00e7\u00e3o":null,"T\u00edtulo":null},"60":{"":null,"Nome completo":null,"Tamb\u00e9m conhecido(a) como":null,"Nascimento":null,"G\u00eanero(s)":"h","Ocupa\u00e7\u00e3o":null,"Instrumento(s)":null,"Per\u00edodo em atividade":null,"Afilia\u00e7\u00e3o(\u00f5es)":null,"P\u00e1gina oficial":null,"Crime(s)":null,"Pena":null,"Situa\u00e7\u00e3o":null,"T\u00edtulo":null},"61":{"":null,"Nome completo":null,"Tamb\u00e9m conhecido(a) como":null,"Nascimento":null,"G\u00eanero(s)":"i","Ocupa\u00e7\u00e3o":null,"Instrumento(s)":null,"Per\u00edodo em atividade":null,"Afilia\u00e7\u00e3o(\u00f5es)":null,"P\u00e1gina oficial":null,"Crime(s)":null,"Pena":null,"Situa\u00e7\u00e3o":null,"T\u00edtulo":null},"62":{"":null,"Nome completo":null,"Tamb\u00e9m conhecido(a) como":null,"Nascimento":null,"G\u00eanero(s)":"p","Ocupa\u00e7\u00e3o":null,"Instrumento(s)":null,"Per\u00edodo em atividade":null,"Afilia\u00e7\u00e3o(\u00f5es)":null,"P\u00e1gina oficial":null,"Crime(s)":null,"Pena":null,"Situa\u00e7\u00e3o":null,"T\u00edtulo":null},"63":{"":null,"Nome completo":null,"Tamb\u00e9m conhecido(a) como":null,"Nascimento":null,"G\u00eanero(s)":" ","Ocupa\u00e7\u00e3o":null,"Instrumento(s)":null,"Per\u00edodo em atividade":null,"Afilia\u00e7\u00e3o(\u00f5es)":null,"P\u00e1gina oficial":null,"Crime(s)":null,"Pena":null,"Situa\u00e7\u00e3o":null,"T\u00edtulo":null},"64":{"":null,"Nome completo":null,"Tamb\u00e9m conhecido(a) como":null,"Nascimento":null,"G\u00eanero(s)":"h","Ocupa\u00e7\u00e3o":null,"Instrumento(s)":null,"Per\u00edodo em atividade":null,"Afilia\u00e7\u00e3o(\u00f5es)":null,"P\u00e1gina oficial":null,"Crime(s)":null,"Pena":null,"Situa\u00e7\u00e3o":null,"T\u00edtulo":null},"65":{"":null,"Nome completo":null,"Tamb\u00e9m conhecido(a) como":null,"Nascimento":null,"G\u00eanero(s)":"o","Ocupa\u00e7\u00e3o":null,"Instrumento(s)":null,"Per\u00edodo em atividade":null,"Afilia\u00e7\u00e3o(\u00f5es)":null,"P\u00e1gina oficial":null,"Crime(s)":null,"Pena":null,"Situa\u00e7\u00e3o":null,"T\u00edtulo":null},"66":{"":null,"Nome completo":null,"Tamb\u00e9m conhecido(a) como":null,"Nascimento":null,"G\u00eanero(s)":"p","Ocupa\u00e7\u00e3o":null,"Instrumento(s)":null,"Per\u00edodo em atividade":null,"Afilia\u00e7\u00e3o(\u00f5es)":null,"P\u00e1gina oficial":null,"Crime(s)":null,"Pena":null,"Situa\u00e7\u00e3o":null,"T\u00edtulo":null},"67":{"":null,"Nome completo":null,"Tamb\u00e9m conhecido(a) como":null,"Nascimento":null,"G\u00eanero(s)":"[","Ocupa\u00e7\u00e3o":null,"Instrumento(s)":null,"Per\u00edodo em atividade":null,"Afilia\u00e7\u00e3o(\u00f5es)":null,"P\u00e1gina oficial":null,"Crime(s)":null,"Pena":null,"Situa\u00e7\u00e3o":null,"T\u00edtulo":null},"68":{"":null,"Nome completo":null,"Tamb\u00e9m conhecido(a) como":null,"Nascimento":null,"G\u00eanero(s)":"2","Ocupa\u00e7\u00e3o":null,"Instrumento(s)":null,"Per\u00edodo em atividade":null,"Afilia\u00e7\u00e3o(\u00f5es)":null,"P\u00e1gina oficial":null,"Crime(s)":null,"Pena":null,"Situa\u00e7\u00e3o":null,"T\u00edtulo":null},"69":{"":null,"Nome completo":null,"Tamb\u00e9m conhecido(a) como":null,"Nascimento":null,"G\u00eanero(s)":"]","Ocupa\u00e7\u00e3o":null,"Instrumento(s)":null,"Per\u00edodo em atividade":null,"Afilia\u00e7\u00e3o(\u00f5es)":null,"P\u00e1gina oficial":null,"Crime(s)":null,"Pena":null,"Situa\u00e7\u00e3o":null,"T\u00edtulo":null}}