{"0":{"Per\u00edodo":"26 de mar\u00e7o de 1977a 28 de julho de 1979","Presidente":"Shankar Dayal Sharma","Antecessor(a)":"Yashwantrao Chavan","Sucessor(a)":"Shyam Nandan Prasad Mishra","Nascimento":"25 de dezembro de 1924 Gwalior, Madhya Pradesh","Morte":"16 de agosto de 2018\u00a0(93\u00a0anos)","Nacionalidade":"indiano","Alma mater":"Victoria College","Partido":"Bharatiya Janata","Religi\u00e3o":"Hindu\u00edsmo","Jawaharlal Nehru\nGulzarilal Nanda\nLal Bahadur Shastri\nGulzarilal Nanda\nIndira Gandhi\nMorarji Desai\nChoudhary Charan Singh\nIndira Gandhi\nRajiv Gandhi\nVishwanath Pratap Singh\nChandra Shekhar\nP. V. Narasimha Rao\nAtal Bihari Vajpayee\nDeve Gowda\nInder Kumar Gujral\nAtal Bihari Vajpayee\nManmohan Singh\nNarendra Modi":"","T\u00edtulo":"Atal Bihari Vajpayee"}}