{"0":{"Hino nacional":"God Save the King\/Queen (Deus Salve o Rei\/Rainha)","Capital":"Calcut\u00e1[2][c](1858\u20131911)Nova Deli(1911\/1931[d]\u20131947)","L\u00ednguas oficiais":["Ingl\u00eas[e]","Hindust\u00e2ni  (Urdu)[f]","Outras l\u00ednguas indianas[g]"],"Moeda":"Rupia indiana (\u20b9)","Forma de governo":"Governo Colonial Brit\u00e2nico","Hist\u00f3ria":"","Outros":"42 763","Bandeira\nBras\u00e3o\nHino\nCinema\nCulin\u00e1ria\nCultura\nDemografia\nEconomia\nFor\u00e7as Armadas\nGeografia\nGoverno\nHist\u00f3ria\nPol\u00edtica\nSubdivis\u00f5es\nTurismo\nImagens\nPortal":"","T\u00edtulo":"Raj Brit\u00e2nicoBritish RajEstrutura pol\u00edtica imperial(compreendendo a \u00cdndia Brit\u00e2nica[a] e os Estados Principescos[b])[1]"}}