{"0":{"Nascimento":"11 de junho de 1952Tabuaeran","Cidadania":"Kiribati","C\u00f4njuge":"Meme Tong","Filho(a)(s)":"Vincent Tong","Alma mater":["Universidade de Canterbury","London School of Economics","St Bede's College"],"Ocupa\u00e7\u00e3o":"pol\u00edtico, diplomata","Distin\u00e7\u00f5es":["Order of Brilliant Jade (2009)"],"Ieremia Tabai\nRota Onorio\nIeremia Tabai\nTeatao Teannaki\nTekiree Tamuera\nAta Teaotai\nTeburoro Tito\nTion Otang\nAnote Tong\nTaneti Maamau":"","T\u00edtulo":"Anote Tong"}}