{"0":{"Capitale maior cidade":"Bisqueque42\u00b0 52\u2032 N, 74\u00b0 34\u2032 L","L\u00edngua oficial":"Quirguiz\nL\u00edngua co-oficial: russo","Gent\u00edlico":"quirguiz;[1]ou quirguistan\u00eas(esa)","Governo":"Rep\u00fablica presidencialista","\u2022 Presidente":"Sadyr Japarov","\u2022 Presidente do Conselho de Ministros":"Adylbek Kasymaliev","\u2022 Declarada":"31 de agosto de 1991","\u2022 Completada":"25 de dezembro de 1991","\u2022 Total":"US$\u00a024,356 bilh\u00f5es (139.\u00ba)","\u2022 \u00c1gua (%)":"3,6","Fronteira":"Cazaquist\u00e3o, China, Tajiquist\u00e3o e Uzbequist\u00e3o","\u2022 Estimativa para 2019":"6,389,500[2] hab. (110.\u00ba)","\u2022 Censo 2009":"5,362,800 hab.","\u2022 Densidade":"26 hab.\/km\u00b2 (176.\u00ba)","PIB (base PPC)":"Estimativa para 2018","\u2022 Per capita":"US$\u00a03,812[2] (147.\u00ba)","IDH (2022)":"0,701 (117.\u00ba) \u2013\u00a0alto[3]","Moeda":"Som quirguiz (KGS)","Fuso hor\u00e1rio":"KGT (UTC+5)","\u2022 Ver\u00e3o\u00a0(DST)":"KGST (UTC+6)","C\u00f3d. Internet":".kg","C\u00f3d. telef.":"+996","Bandeira\nBras\u00e3o\nHino\nCulin\u00e1ria\nCultura\nDemografia\nEconomia\nGeografia\nHist\u00f3ria\nPol\u00edtica\nReligi\u00e3o\nSubdivis\u00f5es\nImagens\nPortal":"","Afeganist\u00e3o\nAr\u00e1bia Saudita\nArm\u00e9nia\nAzerbaij\u00e3o\nBangladesh\nBahrein\nBrunei\nBut\u00e3o\nCamboja\nCatar\nCazaquist\u00e3o\nChina\nChipre\nCoreia do Norte\nCoreia do Sul\nEgito\nEmirados \u00c1rabes Unidos\nFilipinas\nGe\u00f3rgia\nI\u00e9men\n\u00cdndia\nIndon\u00e9sia\nIr\u00e3\nIraque\nIsrael\nJap\u00e3o\nJord\u00e2nia\nKuwait\nLaos\nL\u00edbano\nMaldivas\nMal\u00e1sia\nMong\u00f3lia\nMyanmar\nNepal\nOm\u00e3\nPaquist\u00e3o\nQuirguist\u00e3o\nR\u00fassia\nSingapura\nS\u00edria\nSri Lanka\nTajiquist\u00e3o\nTail\u00e2ndia\nTimor-Leste\nTurquemenist\u00e3o\nTurquia\nUzbequist\u00e3o\nVietn\u00e3":"","Arm\u00eania \u00a0\u2022  Azerbaij\u00e3o \u00a0\u2022  Bielorr\u00fassia \u00a0\u2022  Cazaquist\u00e3o \u00a0\u2022  Quirguist\u00e3o \u00a0\u2022  Mold\u00e1via \u00a0\u2022  R\u00fassia \u00a0\u2022  Tajiquist\u00e3o \u00a0\u2022  Uzbequist\u00e3o":"","T\u00edtulo":"Rep\u00fablica Quirguiz"}}