{"0":{"":"Este artigo cita fontes, mas que n\u00e3o cobrem todo o conte\u00fado. Ajude a inserir refer\u00eancias (Encontre fontes: ABW \u00a0\u2022  CAPES \u00a0\u2022   Google (not\u00edcias\u00a0\u2022 livros\u00a0\u2022 acad\u00eamico)). (Janeiro de 2018)","Capitale maior cidade":"Adis Abeba 4\u00b0 30'N 33\u00b0 48'O","L\u00edngua oficial":"Afar, am\u00e1rico, oromo, somali e tigr\u00ednia[1][2][3]","Gent\u00edlico":"et\u00edope,etiopiano[4]","Governo":"Rep\u00fablica federal parlamentarista\u00b9","\u2022 Presidente":"Taye Atske Selassie","\u2022 Primeiro-ministro":"Abiy Ahmed","\u2022 Reino de D\u02bfmt":"s\u00e9culo XIII a.C.","\u2022 Imp\u00e9rio de Axum":"s\u00e9culo I a.C.","\u2022 Imp\u00e9rio Et\u00edope":"1270 - 1936 \/ 1941 - 1974","\u2022 Ocupa\u00e7\u00e3o Italiana":"Junho de 1936 - novembro de 1941","\u2022 Junta militar":"1974","\u2022 Governo de transi\u00e7\u00e3o":"1991","\u2022 Rep\u00fablica Democr\u00e1tica Federal":"1995","\u2022 Total":"US$\u00a090 968 bilh\u00f5es\u00a0*[6]","\u2022 \u00c1gua (%)":"0,7","Fronteira":"Sud\u00e3o, Sud\u00e3o do Sul, Som\u00e1lia, Eritreia, Djibuti, Qu\u00eania","\u2022 Estimativa para 2023":"107\u00a0334\u00a0000 [5] hab. (13.\u00ba)","\u2022 Censo 2007":"73\u00a0918\u00a0505 hab.","\u2022 Urbana":"1\u00a0346\u00a0757 hab. (186.\u00ba)","\u2022 Densidade":"75 hab.\/km\u00b2 (123.\u00ba)","PIB (base PPC)":"Estimativa para 2019","\u2022 Per capita":"US$\u00a0951[6]","IDH (2021)":"0,498 (175.\u00ba) \u2013\u00a0baixo[7]","Moeda":"Birr Et\u00edope (ETB)","Fuso hor\u00e1rio":"Hor\u00e1rio da \u00c1frica Oriental (UTC+3)","\u2022 Ver\u00e3o\u00a0(DST)":"n\u00e3o verificada (UTC+3)","C\u00f3d. ISO":"ETH","C\u00f3d. Internet":".et","C\u00f3d. telef.":"+251","Bandeira\nBras\u00e3o\nHino\nCulin\u00e1ria\nCultura\nDemografia\nEconomia\nGeografia\nHist\u00f3ria\nPol\u00edtica\nReligi\u00e3o\nRios\nSubdivis\u00f5es\nImagens\nPortal":"","\u00c1frica do Sul\nAngola\nArg\u00e9lia\nBenim\nBotsuana\nBurquina Fasso\nBurundi\nCabo Verde\nCamar\u00f5es\nChade\nComores\nR. Congo\nCosta do Marfim\nDjibuti\nEgito\nEritreia\nEssuat\u00edni\nEti\u00f3pia\nGab\u00e3o\nG\u00e2mbia\nGana\nGuin\u00e9\nGuin\u00e9-Bissau\nGuin\u00e9 Equatorial\nLesoto\nLib\u00e9ria\nL\u00edbia\nMadag\u00e1scar\nMal\u00e1ui\nMali\nMarrocos\nMaur\u00edcia\nMaurit\u00e2nia\nMo\u00e7ambique\nNam\u00edbia\nN\u00edger\nNig\u00e9ria\nQu\u00e9nia\nRep\u00fablica Centro-Africana\nR. D. Congo\nRuanda\nS\u00e3o Tom\u00e9 e Pr\u00edncipe\nSenegal\nSerra Leoa\nSeicheles\nSom\u00e1lia\nSud\u00e3o\nSud\u00e3o do Sul\nTanz\u00e2nia\nTogo\nTun\u00edsia\nUganda\nZ\u00e2mbia\nZimb\u00e1bue":"","Pan-africanismo\nGrupo de Casablanca\nGrupo de Monr\u00f3via\nUni\u00e3o Monet\u00e1ria Africana\nDeclara\u00e7\u00e3o de Sirte\nAto Constitutivo":"","Brasil\nCanad\u00e1\nEstados Unidos\nFran\u00e7a\n\u00cdndia\nNova Zel\u00e2ndia\nPa\u00edses Baixos\nPaquist\u00e3o\nReino Unido":"","T\u00edtulo":"Rep\u00fablica Democr\u00e1tica Federal da Eti\u00f3pia"}}