{"0":{"":"v","Reino:":"A","Filo:":"C","Classe:":"A","Ordem:":"P","Fam\u00edlia:":"C","G\u00e9nero:":"C","T\u00edtulo":"J"},"1":{"":"d","Reino:":"n","Filo:":"h","Classe:":"c","Ordem:":"e","Fam\u00edlia:":"i","G\u00e9nero:":"r","T\u00edtulo":"a"},"2":{"":"e","Reino:":"i","Filo:":"o","Classe:":"t","Ordem:":"r","Fam\u00edlia:":"c","G\u00e9nero:":"e","T\u00edtulo":"c"},"3":{"":null,"Reino:":"m","Filo:":"r","Classe:":"i","Ordem:":"c","Fam\u00edlia:":"h","G\u00e9nero:":"n","T\u00edtulo":"u"},"4":{"":null,"Reino:":"a","Filo:":"d","Classe:":"n","Ordem:":"i","Fam\u00edlia:":"l","G\u00e9nero:":"i","T\u00edtulo":"n"},"5":{"":null,"Reino:":"l","Filo:":"a","Classe:":"o","Ordem:":"f","Fam\u00edlia:":"i","G\u00e9nero:":"c","T\u00edtulo":"d"},"6":{"":null,"Reino:":"i","Filo:":"t","Classe:":"p","Ordem:":"o","Fam\u00edlia:":"d","G\u00e9nero:":"i","T\u00edtulo":"\u00e1"},"7":{"":null,"Reino:":"a","Filo:":"a","Classe:":"t","Ordem:":"r","Fam\u00edlia:":"a","G\u00e9nero:":"c","T\u00edtulo":null},"8":{"":null,"Reino:":null,"Filo:":null,"Classe:":"e","Ordem:":"m","Fam\u00edlia:":"e","G\u00e9nero:":"h","T\u00edtulo":null},"9":{"":null,"Reino:":null,"Filo:":null,"Classe:":"r","Ordem:":"e","Fam\u00edlia:":null,"G\u00e9nero:":"l","T\u00edtulo":null},"10":{"":null,"Reino:":null,"Filo:":null,"Classe:":"y","Ordem:":"s","Fam\u00edlia:":null,"G\u00e9nero:":"a","T\u00edtulo":null},"11":{"":null,"Reino:":null,"Filo:":null,"Classe:":"g","Ordem:":null,"Fam\u00edlia:":null,"G\u00e9nero:":null,"T\u00edtulo":null},"12":{"":null,"Reino:":null,"Filo:":null,"Classe:":"i","Ordem:":null,"Fam\u00edlia:":null,"G\u00e9nero:":null,"T\u00edtulo":null},"13":{"":null,"Reino:":null,"Filo:":null,"Classe:":"i","Ordem:":null,"Fam\u00edlia:":null,"G\u00e9nero:":null,"T\u00edtulo":null}}